ASLTranslator/__init__.py
ASLTranslator/translator.py
ASLTranslator-0.1.0.dist-info/METADATA
ASLTranslator-0.1.0.dist-info/WHEEL
ASLTranslator-0.1.0.dist-info/top_level.txt
ASLTranslator-0.1.0.dist-info/RECORD
